ytty/__init__.py
ytty/ytty.py
ytty-1.0.3.dist-info/LICENSE
ytty-1.0.3.dist-info/METADATA
ytty-1.0.3.dist-info/WHEEL
ytty-1.0.3.dist-info/top_level.txt
ytty-1.0.3.dist-info/RECORD
