Metadata-Version: 2.1
Name: ytty
Version: 1.0.3
Summary: Ytty - Powerful tool for parsing, downloading and uploading videos from youtube based on selenium.
Home-page: https://github.com/DedInc/ytty
Author: Maehdakvan
Author-email: visitanimation@google.com
Project-URL: Bug Tracker, https://github.com/DedInc/ytty/issues
Classifier: Programming Language :: Python :: 3
Classifier: License :: OSI Approved :: MIT License
Classifier: Operating System :: OS Independent
Requires-Python: >=3.6
License-File: LICENSE
Requires-Dist: vidspinner
Requires-Dist: pyperclip
Requires-Dist: undetected-chromedriver
Requires-Dist: requests
Requires-Dist: keyboard
Requires-Dist: pythread
